z007/__init__.py
z007/agent.py
z007/main.py
z007/mcp.json
z007-0.2.1.dist-info/METADATA
z007-0.2.1.dist-info/WHEEL
z007-0.2.1.dist-info/entry_points.txt
z007-0.2.1.dist-info/licenses/LICENSE
z007-0.2.1.dist-info/RECORD
