Metadata-Version: 2.4
Name: z007
Version: 0.2.1
Summary: Micro agent with tool support and MCP integration.
Project-URL: Homepage, https://github.com/okigan/z007
Project-URL: Repository, https://github.com/okigan/z007
Project-URL: Issues, https://github.com/okigan/z007/issues
Project-URL: Changelog, https://github.com/okigan/z007/releases
Author-email: Igor Okulist <okigan@gmail.com>
License: MIT
License-File: LICENSE
Keywords: agent,ai,async,bedrock,llm,mcp,tools
Classifier: Development Status :: 4 - Beta
Classifier: Intended Audience :: Developers
Classifier: License :: OSI Approved :: MIT License
Classifier: Operating System :: OS Independent
Classifier: Programming Language :: Python :: 3
Classifier: Programming Language :: Python :: 3.9
Classifier: Programming Language :: Python :: 3.10
Classifier: Programming Language :: Python :: 3.11
Classifier: Programming Language :: Python :: 3.12
Classifier: Topic :: Scientific/Engineering :: Artificial Intelligence
Classifier: Topic :: Software Development :: Libraries :: Python Modules
Requires-Python: >=3.9
Requires-Dist: anyio>=4.10.0
Requires-Dist: boto3
Requires-Dist: botocore
Requires-Dist: httpx>=0.28.1
Requires-Dist: python-dotenv>=1.0.0
Requires-Dist: rich>=14.1.0
